confluenceexport/__init__.py
confluenceexport/__main__.py
confluenceexport/cli.py
confluenceexport/config.py
confluenceexport/confluenceclient.py
confluenceexport/export.py
confluenceexport/utils.py
confluence_exporter-0.2.0.dist-info/LICENSE
confluence_exporter-0.2.0.dist-info/METADATA
confluence_exporter-0.2.0.dist-info/WHEEL
confluence_exporter-0.2.0.dist-info/entry_points.txt
confluence_exporter-0.2.0.dist-info/top_level.txt
confluence_exporter-0.2.0.dist-info/RECORD
