Metadata-Version: 2.1
Name: confluence-exporter
Version: 0.2.0
Summary: Export Confluence page and convert to others formats
Home-page: https://github.com/cledouarec/confluence-export
Author: Christophe Le Douarec
Author-email: ledouarec@gmail.com
License: Apache License 2.0
Keywords: confluence atlassian extractor
Classifier: Programming Language :: Python :: 3 :: Only
Classifier: License :: OSI Approved :: Apache Software License
Classifier: Operating System :: OS Independent
Classifier: Environment :: Console
Classifier: Topic :: Utilities
License-File: LICENSE
Requires-Dist: atlassian-python-api
Requires-Dist: PyPDF2
Requires-Dist: python-dotenv
Requires-Dist: PyYAML
Provides-Extra: dev
Requires-Dist: coverage ; extra == 'dev'
Requires-Dist: pre-commit ; extra == 'dev'
Requires-Dist: pylint ; extra == 'dev'
Requires-Dist: pytest ; extra == 'dev'
Requires-Dist: pytest-cov ; extra == 'dev'
